PyROQ/__init__.py
PyROQ/pyroq.py
PyROQ-0.1.25.dist-info/LICENSE
PyROQ-0.1.25.dist-info/METADATA
PyROQ-0.1.25.dist-info/WHEEL
PyROQ-0.1.25.dist-info/top_level.txt
PyROQ-0.1.25.dist-info/RECORD
